package com.google.android.gms.internal;

import android.os.Binder;
import android.os.IBinder;
import android.os.IInterface;
import android.os.Parcel;
import android.os.Parcelable.Creator;
import android.os.RemoteException;
import com.google.android.gms.dynamic.zzd;
import com.google.android.gms.dynamic.zzd.zza;

public abstract interface zzep
  extends IInterface
{
  public abstract void destroy()
    throws RemoteException;
  
  public abstract String getMediationAdapterClassName()
    throws RemoteException;
  
  public abstract boolean isLoading()
    throws RemoteException;
  
  public abstract boolean isReady()
    throws RemoteException;
  
  public abstract void pause()
    throws RemoteException;
  
  public abstract void resume()
    throws RemoteException;
  
  public abstract void setManualImpressionsEnabled(boolean paramBoolean)
    throws RemoteException;
  
  public abstract void setUserId(String paramString)
    throws RemoteException;
  
  public abstract void showInterstitial()
    throws RemoteException;
  
  public abstract void stopLoading()
    throws RemoteException;
  
  public abstract void zza(zzec paramZzec)
    throws RemoteException;
  
  public abstract void zza(zzek paramZzek)
    throws RemoteException;
  
  public abstract void zza(zzel paramZzel)
    throws RemoteException;
  
  public abstract void zza(zzer paramZzer)
    throws RemoteException;
  
  public abstract void zza(zzet paramZzet)
    throws RemoteException;
  
  public abstract void zza(zzfn paramZzfn)
    throws RemoteException;
  
  public abstract void zza(zzgj paramZzgj)
    throws RemoteException;
  
  public abstract void zza(zzkz paramZzkz)
    throws RemoteException;
  
  public abstract void zza(zzld paramZzld, String paramString)
    throws RemoteException;
  
  public abstract void zza(zznt paramZznt)
    throws RemoteException;
  
  public abstract boolean zzb(zzdy paramZzdy)
    throws RemoteException;
  
  public abstract zzd zzbC()
    throws RemoteException;
  
  public abstract zzec zzbD()
    throws RemoteException;
  
  public abstract void zzbF()
    throws RemoteException;
  
  public abstract zzew zzbG()
    throws RemoteException;
  
  public static abstract class zza
    extends Binder
    implements zzep
  {
    public zza()
    {
      attachInterface(this, "com.google.android.gms.ads.internal.client.IAdManager");
    }
    
    public static zzep zzq(IBinder paramIBinder)
    {
      if (paramIBinder == null) {
        return null;
      }
      IInterface localIInterface = paramIBinder.queryLocalInterface("com.google.android.gms.ads.internal.client.IAdManager");
      if ((localIInterface != null) && ((localIInterface instanceof zzep))) {
        return (zzep)localIInterface;
      }
      return new zza(paramIBinder);
    }
    
    public IBinder asBinder()
    {
      return this;
    }
    
    public boolean onTransact(int paramInt1, Parcel paramParcel1, Parcel paramParcel2, int paramInt2)
      throws RemoteException
    {
      Object localObject2 = null;
      Object localObject3 = null;
      zzd localZzd = null;
      Object localObject4 = null;
      Object localObject1 = null;
      boolean bool = false;
      int j = 0;
      int i = 0;
      switch (paramInt1)
      {
      default: 
        return super.onTransact(paramInt1, paramParcel1, paramParcel2, paramInt2);
      case 1598968902: 
        paramParcel2.writeString("com.google.android.gms.ads.internal.client.IAdManager");
        return true;
      case 1: 
        paramParcel1.enforceInterface("com.google.android.gms.ads.internal.client.IAdManager");
        localZzd = zzbC();
        paramParcel2.writeNoException();
        paramParcel1 = (Parcel)localObject1;
        if (localZzd != null) {
          paramParcel1 = localZzd.asBinder();
        }
        paramParcel2.writeStrongBinder(paramParcel1);
        return true;
      case 2: 
        paramParcel1.enforceInterface("com.google.android.gms.ads.internal.client.IAdManager");
        destroy();
        paramParcel2.writeNoException();
        return true;
      case 3: 
        paramParcel1.enforceInterface("com.google.android.gms.ads.internal.client.IAdManager");
        bool = isReady();
        paramParcel2.writeNoException();
        if (bool) {}
        for (paramInt1 = 1;; paramInt1 = 0)
        {
          paramParcel2.writeInt(paramInt1);
          return true;
        }
      case 4: 
        paramParcel1.enforceInterface("com.google.android.gms.ads.internal.client.IAdManager");
        localObject1 = localObject2;
        if (paramParcel1.readInt() != 0) {
          localObject1 = (zzdy)zzdy.CREATOR.createFromParcel(paramParcel1);
        }
        bool = zzb((zzdy)localObject1);
        paramParcel2.writeNoException();
        paramInt1 = i;
        if (bool) {
          paramInt1 = 1;
        }
        paramParcel2.writeInt(paramInt1);
        return true;
      case 5: 
        paramParcel1.enforceInterface("com.google.android.gms.ads.internal.client.IAdManager");
        pause();
        paramParcel2.writeNoException();
        return true;
      case 6: 
        paramParcel1.enforceInterface("com.google.android.gms.ads.internal.client.IAdManager");
        resume();
        paramParcel2.writeNoException();
        return true;
      case 7: 
        paramParcel1.enforceInterface("com.google.android.gms.ads.internal.client.IAdManager");
        zza(zzel.zza.zzm(paramParcel1.readStrongBinder()));
        paramParcel2.writeNoException();
        return true;
      case 8: 
        paramParcel1.enforceInterface("com.google.android.gms.ads.internal.client.IAdManager");
        zza(zzer.zza.zzs(paramParcel1.readStrongBinder()));
        paramParcel2.writeNoException();
        return true;
      case 9: 
        paramParcel1.enforceInterface("com.google.android.gms.ads.internal.client.IAdManager");
        showInterstitial();
        paramParcel2.writeNoException();
        return true;
      case 10: 
        paramParcel1.enforceInterface("com.google.android.gms.ads.internal.client.IAdManager");
        stopLoading();
        paramParcel2.writeNoException();
        return true;
      case 11: 
        paramParcel1.enforceInterface("com.google.android.gms.ads.internal.client.IAdManager");
        zzbF();
        paramParcel2.writeNoException();
        return true;
      case 12: 
        paramParcel1.enforceInterface("com.google.android.gms.ads.internal.client.IAdManager");
        paramParcel1 = zzbD();
        paramParcel2.writeNoException();
        if (paramParcel1 != null)
        {
          paramParcel2.writeInt(1);
          paramParcel1.writeToParcel(paramParcel2, 1);
          return true;
        }
        paramParcel2.writeInt(0);
        return true;
      case 13: 
        paramParcel1.enforceInterface("com.google.android.gms.ads.internal.client.IAdManager");
        localObject1 = localObject3;
        if (paramParcel1.readInt() != 0) {
          localObject1 = (zzec)zzec.CREATOR.createFromParcel(paramParcel1);
        }
        zza((zzec)localObject1);
        paramParcel2.writeNoException();
        return true;
      case 14: 
        paramParcel1.enforceInterface("com.google.android.gms.ads.internal.client.IAdManager");
        zza(zzkz.zza.zzX(paramParcel1.readStrongBinder()));
        paramParcel2.writeNoException();
        return true;
      case 15: 
        paramParcel1.enforceInterface("com.google.android.gms.ads.internal.client.IAdManager");
        zza(zzld.zza.zzab(paramParcel1.readStrongBinder()), paramParcel1.readString());
        paramParcel2.writeNoException();
        return true;
      case 18: 
        paramParcel1.enforceInterface("com.google.android.gms.ads.internal.client.IAdManager");
        paramParcel1 = getMediationAdapterClassName();
        paramParcel2.writeNoException();
        paramParcel2.writeString(paramParcel1);
        return true;
      case 19: 
        paramParcel1.enforceInterface("com.google.android.gms.ads.internal.client.IAdManager");
        zza(zzgj.zza.zzA(paramParcel1.readStrongBinder()));
        paramParcel2.writeNoException();
        return true;
      case 20: 
        paramParcel1.enforceInterface("com.google.android.gms.ads.internal.client.IAdManager");
        zza(zzek.zza.zzl(paramParcel1.readStrongBinder()));
        paramParcel2.writeNoException();
        return true;
      case 21: 
        paramParcel1.enforceInterface("com.google.android.gms.ads.internal.client.IAdManager");
        zza(zzet.zza.zzt(paramParcel1.readStrongBinder()));
        paramParcel2.writeNoException();
        return true;
      case 22: 
        paramParcel1.enforceInterface("com.google.android.gms.ads.internal.client.IAdManager");
        if (paramParcel1.readInt() != 0) {
          bool = true;
        }
        setManualImpressionsEnabled(bool);
        paramParcel2.writeNoException();
        return true;
      case 23: 
        paramParcel1.enforceInterface("com.google.android.gms.ads.internal.client.IAdManager");
        bool = isLoading();
        paramParcel2.writeNoException();
        paramInt1 = j;
        if (bool) {
          paramInt1 = 1;
        }
        paramParcel2.writeInt(paramInt1);
        return true;
      case 24: 
        paramParcel1.enforceInterface("com.google.android.gms.ads.internal.client.IAdManager");
        zza(zznt.zza.zzaj(paramParcel1.readStrongBinder()));
        paramParcel2.writeNoException();
        return true;
      case 25: 
        paramParcel1.enforceInterface("com.google.android.gms.ads.internal.client.IAdManager");
        setUserId(paramParcel1.readString());
        paramParcel2.writeNoException();
        return true;
      case 26: 
        paramParcel1.enforceInterface("com.google.android.gms.ads.internal.client.IAdManager");
        localObject1 = zzbG();
        paramParcel2.writeNoException();
        paramParcel1 = localZzd;
        if (localObject1 != null) {
          paramParcel1 = ((zzew)localObject1).asBinder();
        }
        paramParcel2.writeStrongBinder(paramParcel1);
        return true;
      }
      paramParcel1.enforceInterface("com.google.android.gms.ads.internal.client.IAdManager");
      localObject1 = localObject4;
      if (paramParcel1.readInt() != 0) {
        localObject1 = (zzfn)zzfn.CREATOR.createFromParcel(paramParcel1);
      }
      zza((zzfn)localObject1);
      paramParcel2.writeNoException();
      return true;
    }
    
    private static class zza
      implements zzep
    {
      private IBinder zzrp;
      
      zza(IBinder paramIBinder)
      {
        zzrp = paramIBinder;
      }
      
      public IBinder asBinder()
      {
        return zzrp;
      }
      
      public void destroy()
        throws RemoteException
      {
        Parcel localParcel1 = Parcel.obtain();
        Parcel localParcel2 = Parcel.obtain();
        try
        {
          localParcel1.writeInterfaceToken("com.google.android.gms.ads.internal.client.IAdManager");
          zzrp.transact(2, localParcel1, localParcel2, 0);
          localParcel2.readException();
          return;
        }
        finally
        {
          localParcel2.recycle();
          localParcel1.recycle();
        }
      }
      
      public String getMediationAdapterClassName()
        throws RemoteException
      {
        Parcel localParcel1 = Parcel.obtain();
        Parcel localParcel2 = Parcel.obtain();
        try
        {
          localParcel1.writeInterfaceToken("com.google.android.gms.ads.internal.client.IAdManager");
          zzrp.transact(18, localParcel1, localParcel2, 0);
          localParcel2.readException();
          String str = localParcel2.readString();
          return str;
        }
        finally
        {
          localParcel2.recycle();
          localParcel1.recycle();
        }
      }
      
      public boolean isLoading()
        throws RemoteException
      {
        boolean bool = false;
        Parcel localParcel1 = Parcel.obtain();
        Parcel localParcel2 = Parcel.obtain();
        try
        {
          localParcel1.writeInterfaceToken("com.google.android.gms.ads.internal.client.IAdManager");
          zzrp.transact(23, localParcel1, localParcel2, 0);
          localParcel2.readException();
          int i = localParcel2.readInt();
          if (i != 0) {
            bool = true;
          }
          return bool;
        }
        finally
        {
          localParcel2.recycle();
          localParcel1.recycle();
        }
      }
      
      public boolean isReady()
        throws RemoteException
      {
        boolean bool = false;
        Parcel localParcel1 = Parcel.obtain();
        Parcel localParcel2 = Parcel.obtain();
        try
        {
          localParcel1.writeInterfaceToken("com.google.android.gms.ads.internal.client.IAdManager");
          zzrp.transact(3, localParcel1, localParcel2, 0);
          localParcel2.readException();
          int i = localParcel2.readInt();
          if (i != 0) {
            bool = true;
          }
          return bool;
        }
        finally
        {
          localParcel2.recycle();
          localParcel1.recycle();
        }
      }
      
      public void pause()
        throws RemoteException
      {
        Parcel localParcel1 = Parcel.obtain();
        Parcel localParcel2 = Parcel.obtain();
        try
        {
          localParcel1.writeInterfaceToken("com.google.android.gms.ads.internal.client.IAdManager");
          zzrp.transact(5, localParcel1, localParcel2, 0);
          localParcel2.readException();
          return;
        }
        finally
        {
          localParcel2.recycle();
          localParcel1.recycle();
        }
      }
      
      public void resume()
        throws RemoteException
      {
        Parcel localParcel1 = Parcel.obtain();
        Parcel localParcel2 = Parcel.obtain();
        try
        {
          localParcel1.writeInterfaceToken("com.google.android.gms.ads.internal.client.IAdManager");
          zzrp.transact(6, localParcel1, localParcel2, 0);
          localParcel2.readException();
          return;
        }
        finally
        {
          localParcel2.recycle();
          localParcel1.recycle();
        }
      }
      
      public void setManualImpressionsEnabled(boolean paramBoolean)
        throws RemoteException
      {
        int i = 0;
        Parcel localParcel1 = Parcel.obtain();
        Parcel localParcel2 = Parcel.obtain();
        try
        {
          localParcel1.writeInterfaceToken("com.google.android.gms.ads.internal.client.IAdManager");
          if (paramBoolean) {
            i = 1;
          }
          localParcel1.writeInt(i);
          zzrp.transact(22, localParcel1, localParcel2, 0);
          localParcel2.readException();
          return;
        }
        finally
        {
          localParcel2.recycle();
          localParcel1.recycle();
        }
      }
      
      public void setUserId(String paramString)
        throws RemoteException
      {
        Parcel localParcel1 = Parcel.obtain();
        Parcel localParcel2 = Parcel.obtain();
        try
        {
          localParcel1.writeInterfaceToken("com.google.android.gms.ads.internal.client.IAdManager");
          localParcel1.writeString(paramString);
          zzrp.transact(25, localParcel1, localParcel2, 0);
          localParcel2.readException();
          return;
        }
        finally
        {
          localParcel2.recycle();
          localParcel1.recycle();
        }
      }
      
      public void showInterstitial()
        throws RemoteException
      {
        Parcel localParcel1 = Parcel.obtain();
        Parcel localParcel2 = Parcel.obtain();
        try
        {
          localParcel1.writeInterfaceToken("com.google.android.gms.ads.internal.client.IAdManager");
          zzrp.transact(9, localParcel1, localParcel2, 0);
          localParcel2.readException();
          return;
        }
        finally
        {
          localParcel2.recycle();
          localParcel1.recycle();
        }
      }
      
      public void stopLoading()
        throws RemoteException
      {
        Parcel localParcel1 = Parcel.obtain();
        Parcel localParcel2 = Parcel.obtain();
        try
        {
          localParcel1.writeInterfaceToken("com.google.android.gms.ads.internal.client.IAdManager");
          zzrp.transact(10, localParcel1, localParcel2, 0);
          localParcel2.readException();
          return;
        }
        finally
        {
          localParcel2.recycle();
          localParcel1.recycle();
        }
      }
      
      /* Error */
      public void zza(zzec paramZzec)
        throws RemoteException
      {
        // Byte code:
        //   0: invokestatic 30	android/os/Parcel:obtain	()Landroid/os/Parcel;
        //   3: astore_2
        //   4: invokestatic 30	android/os/Parcel:obtain	()Landroid/os/Parcel;
        //   7: astore_3
        //   8: aload_2
        //   9: ldc 32
        //   11: invokevirtual 36	android/os/Parcel:writeInterfaceToken	(Ljava/lang/String;)V
        //   14: aload_1
        //   15: ifnull +42 -> 57
        //   18: aload_2
        //   19: iconst_1
        //   20: invokevirtual 69	android/os/Parcel:writeInt	(I)V
        //   23: aload_1
        //   24: aload_2
        //   25: iconst_0
        //   26: invokevirtual 82	com/google/android/gms/internal/zzec:writeToParcel	(Landroid/os/Parcel;I)V
        //   29: aload_0
        //   30: getfield 18	com/google/android/gms/internal/zzep$zza$zza:zzrp	Landroid/os/IBinder;
        //   33: bipush 13
        //   35: aload_2
        //   36: aload_3
        //   37: iconst_0
        //   38: invokeinterface 42 5 0
        //   43: pop
        //   44: aload_3
        //   45: invokevirtual 45	android/os/Parcel:readException	()V
        //   48: aload_3
        //   49: invokevirtual 48	android/os/Parcel:recycle	()V
        //   52: aload_2
        //   53: invokevirtual 48	android/os/Parcel:recycle	()V
        //   56: return
        //   57: aload_2
        //   58: iconst_0
        //   59: invokevirtual 69	android/os/Parcel:writeInt	(I)V
        //   62: goto -33 -> 29
        //   65: astore_1
        //   66: aload_3
        //   67: invokevirtual 48	android/os/Parcel:recycle	()V
        //   70: aload_2
        //   71: invokevirtual 48	android/os/Parcel:recycle	()V
        //   74: aload_1
        //   75: athrow
        // Local variable table:
        //   start	length	slot	name	signature
        //   0	76	0	this	zza
        //   0	76	1	paramZzec	zzec
        //   3	68	2	localParcel1	Parcel
        //   7	60	3	localParcel2	Parcel
        // Exception table:
        //   from	to	target	type
        //   8	14	65	finally
        //   18	29	65	finally
        //   29	48	65	finally
        //   57	62	65	finally
      }
      
      /* Error */
      public void zza(zzek paramZzek)
        throws RemoteException
      {
        // Byte code:
        //   0: invokestatic 30	android/os/Parcel:obtain	()Landroid/os/Parcel;
        //   3: astore_2
        //   4: invokestatic 30	android/os/Parcel:obtain	()Landroid/os/Parcel;
        //   7: astore_3
        //   8: aload_2
        //   9: ldc 32
        //   11: invokevirtual 36	android/os/Parcel:writeInterfaceToken	(Ljava/lang/String;)V
        //   14: aload_1
        //   15: ifnull +43 -> 58
        //   18: aload_1
        //   19: invokeinterface 87 1 0
        //   24: astore_1
        //   25: aload_2
        //   26: aload_1
        //   27: invokevirtual 90	android/os/Parcel:writeStrongBinder	(Landroid/os/IBinder;)V
        //   30: aload_0
        //   31: getfield 18	com/google/android/gms/internal/zzep$zza$zza:zzrp	Landroid/os/IBinder;
        //   34: bipush 20
        //   36: aload_2
        //   37: aload_3
        //   38: iconst_0
        //   39: invokeinterface 42 5 0
        //   44: pop
        //   45: aload_3
        //   46: invokevirtual 45	android/os/Parcel:readException	()V
        //   49: aload_3
        //   50: invokevirtual 48	android/os/Parcel:recycle	()V
        //   53: aload_2
        //   54: invokevirtual 48	android/os/Parcel:recycle	()V
        //   57: return
        //   58: aconst_null
        //   59: astore_1
        //   60: goto -35 -> 25
        //   63: astore_1
        //   64: aload_3
        //   65: invokevirtual 48	android/os/Parcel:recycle	()V
        //   68: aload_2
        //   69: invokevirtual 48	android/os/Parcel:recycle	()V
        //   72: aload_1
        //   73: athrow
        // Local variable table:
        //   start	length	slot	name	signature
        //   0	74	0	this	zza
        //   0	74	1	paramZzek	zzek
        //   3	66	2	localParcel1	Parcel
        //   7	58	3	localParcel2	Parcel
        // Exception table:
        //   from	to	target	type
        //   8	14	63	finally
        //   18	25	63	finally
        //   25	49	63	finally
      }
      
      /* Error */
      public void zza(zzel paramZzel)
        throws RemoteException
      {
        // Byte code:
        //   0: invokestatic 30	android/os/Parcel:obtain	()Landroid/os/Parcel;
        //   3: astore_2
        //   4: invokestatic 30	android/os/Parcel:obtain	()Landroid/os/Parcel;
        //   7: astore_3
        //   8: aload_2
        //   9: ldc 32
        //   11: invokevirtual 36	android/os/Parcel:writeInterfaceToken	(Ljava/lang/String;)V
        //   14: aload_1
        //   15: ifnull +43 -> 58
        //   18: aload_1
        //   19: invokeinterface 94 1 0
        //   24: astore_1
        //   25: aload_2
        //   26: aload_1
        //   27: invokevirtual 90	android/os/Parcel:writeStrongBinder	(Landroid/os/IBinder;)V
        //   30: aload_0
        //   31: getfield 18	com/google/android/gms/internal/zzep$zza$zza:zzrp	Landroid/os/IBinder;
        //   34: bipush 7
        //   36: aload_2
        //   37: aload_3
        //   38: iconst_0
        //   39: invokeinterface 42 5 0
        //   44: pop
        //   45: aload_3
        //   46: invokevirtual 45	android/os/Parcel:readException	()V
        //   49: aload_3
        //   50: invokevirtual 48	android/os/Parcel:recycle	()V
        //   53: aload_2
        //   54: invokevirtual 48	android/os/Parcel:recycle	()V
        //   57: return
        //   58: aconst_null
        //   59: astore_1
        //   60: goto -35 -> 25
        //   63: astore_1
        //   64: aload_3
        //   65: invokevirtual 48	android/os/Parcel:recycle	()V
        //   68: aload_2
        //   69: invokevirtual 48	android/os/Parcel:recycle	()V
        //   72: aload_1
        //   73: athrow
        // Local variable table:
        //   start	length	slot	name	signature
        //   0	74	0	this	zza
        //   0	74	1	paramZzel	zzel
        //   3	66	2	localParcel1	Parcel
        //   7	58	3	localParcel2	Parcel
        // Exception table:
        //   from	to	target	type
        //   8	14	63	finally
        //   18	25	63	finally
        //   25	49	63	finally
      }
      
      /* Error */
      public void zza(zzer paramZzer)
        throws RemoteException
      {
        // Byte code:
        //   0: invokestatic 30	android/os/Parcel:obtain	()Landroid/os/Parcel;
        //   3: astore_2
        //   4: invokestatic 30	android/os/Parcel:obtain	()Landroid/os/Parcel;
        //   7: astore_3
        //   8: aload_2
        //   9: ldc 32
        //   11: invokevirtual 36	android/os/Parcel:writeInterfaceToken	(Ljava/lang/String;)V
        //   14: aload_1
        //   15: ifnull +43 -> 58
        //   18: aload_1
        //   19: invokeinterface 98 1 0
        //   24: astore_1
        //   25: aload_2
        //   26: aload_1
        //   27: invokevirtual 90	android/os/Parcel:writeStrongBinder	(Landroid/os/IBinder;)V
        //   30: aload_0
        //   31: getfield 18	com/google/android/gms/internal/zzep$zza$zza:zzrp	Landroid/os/IBinder;
        //   34: bipush 8
        //   36: aload_2
        //   37: aload_3
        //   38: iconst_0
        //   39: invokeinterface 42 5 0
        //   44: pop
        //   45: aload_3
        //   46: invokevirtual 45	android/os/Parcel:readException	()V
        //   49: aload_3
        //   50: invokevirtual 48	android/os/Parcel:recycle	()V
        //   53: aload_2
        //   54: invokevirtual 48	android/os/Parcel:recycle	()V
        //   57: return
        //   58: aconst_null
        //   59: astore_1
        //   60: goto -35 -> 25
        //   63: astore_1
        //   64: aload_3
        //   65: invokevirtual 48	android/os/Parcel:recycle	()V
        //   68: aload_2
        //   69: invokevirtual 48	android/os/Parcel:recycle	()V
        //   72: aload_1
        //   73: athrow
        // Local variable table:
        //   start	length	slot	name	signature
        //   0	74	0	this	zza
        //   0	74	1	paramZzer	zzer
        //   3	66	2	localParcel1	Parcel
        //   7	58	3	localParcel2	Parcel
        // Exception table:
        //   from	to	target	type
        //   8	14	63	finally
        //   18	25	63	finally
        //   25	49	63	finally
      }
      
      /* Error */
      public void zza(zzet paramZzet)
        throws RemoteException
      {
        // Byte code:
        //   0: invokestatic 30	android/os/Parcel:obtain	()Landroid/os/Parcel;
        //   3: astore_2
        //   4: invokestatic 30	android/os/Parcel:obtain	()Landroid/os/Parcel;
        //   7: astore_3
        //   8: aload_2
        //   9: ldc 32
        //   11: invokevirtual 36	android/os/Parcel:writeInterfaceToken	(Ljava/lang/String;)V
        //   14: aload_1
        //   15: ifnull +43 -> 58
        //   18: aload_1
        //   19: invokeinterface 102 1 0
        //   24: astore_1
        //   25: aload_2
        //   26: aload_1
        //   27: invokevirtual 90	android/os/Parcel:writeStrongBinder	(Landroid/os/IBinder;)V
        //   30: aload_0
        //   31: getfield 18	com/google/android/gms/internal/zzep$zza$zza:zzrp	Landroid/os/IBinder;
        //   34: bipush 21
        //   36: aload_2
        //   37: aload_3
        //   38: iconst_0
        //   39: invokeinterface 42 5 0
        //   44: pop
        //   45: aload_3
        //   46: invokevirtual 45	android/os/Parcel:readException	()V
        //   49: aload_3
        //   50: invokevirtual 48	android/os/Parcel:recycle	()V
        //   53: aload_2
        //   54: invokevirtual 48	android/os/Parcel:recycle	()V
        //   57: return
        //   58: aconst_null
        //   59: astore_1
        //   60: goto -35 -> 25
        //   63: astore_1
        //   64: aload_3
        //   65: invokevirtual 48	android/os/Parcel:recycle	()V
        //   68: aload_2
        //   69: invokevirtual 48	android/os/Parcel:recycle	()V
        //   72: aload_1
        //   73: athrow
        // Local variable table:
        //   start	length	slot	name	signature
        //   0	74	0	this	zza
        //   0	74	1	paramZzet	zzet
        //   3	66	2	localParcel1	Parcel
        //   7	58	3	localParcel2	Parcel
        // Exception table:
        //   from	to	target	type
        //   8	14	63	finally
        //   18	25	63	finally
        //   25	49	63	finally
      }
      
      /* Error */
      public void zza(zzfn paramZzfn)
        throws RemoteException
      {
        // Byte code:
        //   0: invokestatic 30	android/os/Parcel:obtain	()Landroid/os/Parcel;
        //   3: astore_2
        //   4: invokestatic 30	android/os/Parcel:obtain	()Landroid/os/Parcel;
        //   7: astore_3
        //   8: aload_2
        //   9: ldc 32
        //   11: invokevirtual 36	android/os/Parcel:writeInterfaceToken	(Ljava/lang/String;)V
        //   14: aload_1
        //   15: ifnull +42 -> 57
        //   18: aload_2
        //   19: iconst_1
        //   20: invokevirtual 69	android/os/Parcel:writeInt	(I)V
        //   23: aload_1
        //   24: aload_2
        //   25: iconst_0
        //   26: invokevirtual 106	com/google/android/gms/internal/zzfn:writeToParcel	(Landroid/os/Parcel;I)V
        //   29: aload_0
        //   30: getfield 18	com/google/android/gms/internal/zzep$zza$zza:zzrp	Landroid/os/IBinder;
        //   33: bipush 29
        //   35: aload_2
        //   36: aload_3
        //   37: iconst_0
        //   38: invokeinterface 42 5 0
        //   43: pop
        //   44: aload_3
        //   45: invokevirtual 45	android/os/Parcel:readException	()V
        //   48: aload_3
        //   49: invokevirtual 48	android/os/Parcel:recycle	()V
        //   52: aload_2
        //   53: invokevirtual 48	android/os/Parcel:recycle	()V
        //   56: return
        //   57: aload_2
        //   58: iconst_0
        //   59: invokevirtual 69	android/os/Parcel:writeInt	(I)V
        //   62: goto -33 -> 29
        //   65: astore_1
        //   66: aload_3
        //   67: invokevirtual 48	android/os/Parcel:recycle	()V
        //   70: aload_2
        //   71: invokevirtual 48	android/os/Parcel:recycle	()V
        //   74: aload_1
        //   75: athrow
        // Local variable table:
        //   start	length	slot	name	signature
        //   0	76	0	this	zza
        //   0	76	1	paramZzfn	zzfn
        //   3	68	2	localParcel1	Parcel
        //   7	60	3	localParcel2	Parcel
        // Exception table:
        //   from	to	target	type
        //   8	14	65	finally
        //   18	29	65	finally
        //   29	48	65	finally
        //   57	62	65	finally
      }
      
      /* Error */
      public void zza(zzgj paramZzgj)
        throws RemoteException
      {
        // Byte code:
        //   0: invokestatic 30	android/os/Parcel:obtain	()Landroid/os/Parcel;
        //   3: astore_2
        //   4: invokestatic 30	android/os/Parcel:obtain	()Landroid/os/Parcel;
        //   7: astore_3
        //   8: aload_2
        //   9: ldc 32
        //   11: invokevirtual 36	android/os/Parcel:writeInterfaceToken	(Ljava/lang/String;)V
        //   14: aload_1
        //   15: ifnull +43 -> 58
        //   18: aload_1
        //   19: invokeinterface 110 1 0
        //   24: astore_1
        //   25: aload_2
        //   26: aload_1
        //   27: invokevirtual 90	android/os/Parcel:writeStrongBinder	(Landroid/os/IBinder;)V
        //   30: aload_0
        //   31: getfield 18	com/google/android/gms/internal/zzep$zza$zza:zzrp	Landroid/os/IBinder;
        //   34: bipush 19
        //   36: aload_2
        //   37: aload_3
        //   38: iconst_0
        //   39: invokeinterface 42 5 0
        //   44: pop
        //   45: aload_3
        //   46: invokevirtual 45	android/os/Parcel:readException	()V
        //   49: aload_3
        //   50: invokevirtual 48	android/os/Parcel:recycle	()V
        //   53: aload_2
        //   54: invokevirtual 48	android/os/Parcel:recycle	()V
        //   57: return
        //   58: aconst_null
        //   59: astore_1
        //   60: goto -35 -> 25
        //   63: astore_1
        //   64: aload_3
        //   65: invokevirtual 48	android/os/Parcel:recycle	()V
        //   68: aload_2
        //   69: invokevirtual 48	android/os/Parcel:recycle	()V
        //   72: aload_1
        //   73: athrow
        // Local variable table:
        //   start	length	slot	name	signature
        //   0	74	0	this	zza
        //   0	74	1	paramZzgj	zzgj
        //   3	66	2	localParcel1	Parcel
        //   7	58	3	localParcel2	Parcel
        // Exception table:
        //   from	to	target	type
        //   8	14	63	finally
        //   18	25	63	finally
        //   25	49	63	finally
      }
      
      /* Error */
      public void zza(zzkz paramZzkz)
        throws RemoteException
      {
        // Byte code:
        //   0: invokestatic 30	android/os/Parcel:obtain	()Landroid/os/Parcel;
        //   3: astore_2
        //   4: invokestatic 30	android/os/Parcel:obtain	()Landroid/os/Parcel;
        //   7: astore_3
        //   8: aload_2
        //   9: ldc 32
        //   11: invokevirtual 36	android/os/Parcel:writeInterfaceToken	(Ljava/lang/String;)V
        //   14: aload_1
        //   15: ifnull +43 -> 58
        //   18: aload_1
        //   19: invokeinterface 114 1 0
        //   24: astore_1
        //   25: aload_2
        //   26: aload_1
        //   27: invokevirtual 90	android/os/Parcel:writeStrongBinder	(Landroid/os/IBinder;)V
        //   30: aload_0
        //   31: getfield 18	com/google/android/gms/internal/zzep$zza$zza:zzrp	Landroid/os/IBinder;
        //   34: bipush 14
        //   36: aload_2
        //   37: aload_3
        //   38: iconst_0
        //   39: invokeinterface 42 5 0
        //   44: pop
        //   45: aload_3
        //   46: invokevirtual 45	android/os/Parcel:readException	()V
        //   49: aload_3
        //   50: invokevirtual 48	android/os/Parcel:recycle	()V
        //   53: aload_2
        //   54: invokevirtual 48	android/os/Parcel:recycle	()V
        //   57: return
        //   58: aconst_null
        //   59: astore_1
        //   60: goto -35 -> 25
        //   63: astore_1
        //   64: aload_3
        //   65: invokevirtual 48	android/os/Parcel:recycle	()V
        //   68: aload_2
        //   69: invokevirtual 48	android/os/Parcel:recycle	()V
        //   72: aload_1
        //   73: athrow
        // Local variable table:
        //   start	length	slot	name	signature
        //   0	74	0	this	zza
        //   0	74	1	paramZzkz	zzkz
        //   3	66	2	localParcel1	Parcel
        //   7	58	3	localParcel2	Parcel
        // Exception table:
        //   from	to	target	type
        //   8	14	63	finally
        //   18	25	63	finally
        //   25	49	63	finally
      }
      
      /* Error */
      public void zza(zzld paramZzld, String paramString)
        throws RemoteException
      {
        // Byte code:
        //   0: invokestatic 30	android/os/Parcel:obtain	()Landroid/os/Parcel;
        //   3: astore_3
        //   4: invokestatic 30	android/os/Parcel:obtain	()Landroid/os/Parcel;
        //   7: astore 4
        //   9: aload_3
        //   10: ldc 32
        //   12: invokevirtual 36	android/os/Parcel:writeInterfaceToken	(Ljava/lang/String;)V
        //   15: aload_1
        //   16: ifnull +51 -> 67
        //   19: aload_1
        //   20: invokeinterface 118 1 0
        //   25: astore_1
        //   26: aload_3
        //   27: aload_1
        //   28: invokevirtual 90	android/os/Parcel:writeStrongBinder	(Landroid/os/IBinder;)V
        //   31: aload_3
        //   32: aload_2
        //   33: invokevirtual 73	android/os/Parcel:writeString	(Ljava/lang/String;)V
        //   36: aload_0
        //   37: getfield 18	com/google/android/gms/internal/zzep$zza$zza:zzrp	Landroid/os/IBinder;
        //   40: bipush 15
        //   42: aload_3
        //   43: aload 4
        //   45: iconst_0
        //   46: invokeinterface 42 5 0
        //   51: pop
        //   52: aload 4
        //   54: invokevirtual 45	android/os/Parcel:readException	()V
        //   57: aload 4
        //   59: invokevirtual 48	android/os/Parcel:recycle	()V
        //   62: aload_3
        //   63: invokevirtual 48	android/os/Parcel:recycle	()V
        //   66: return
        //   67: aconst_null
        //   68: astore_1
        //   69: goto -43 -> 26
        //   72: astore_1
        //   73: aload 4
        //   75: invokevirtual 48	android/os/Parcel:recycle	()V
        //   78: aload_3
        //   79: invokevirtual 48	android/os/Parcel:recycle	()V
        //   82: aload_1
        //   83: athrow
        // Local variable table:
        //   start	length	slot	name	signature
        //   0	84	0	this	zza
        //   0	84	1	paramZzld	zzld
        //   0	84	2	paramString	String
        //   3	76	3	localParcel1	Parcel
        //   7	67	4	localParcel2	Parcel
        // Exception table:
        //   from	to	target	type
        //   9	15	72	finally
        //   19	26	72	finally
        //   26	57	72	finally
      }
      
      /* Error */
      public void zza(zznt paramZznt)
        throws RemoteException
      {
        // Byte code:
        //   0: invokestatic 30	android/os/Parcel:obtain	()Landroid/os/Parcel;
        //   3: astore_2
        //   4: invokestatic 30	android/os/Parcel:obtain	()Landroid/os/Parcel;
        //   7: astore_3
        //   8: aload_2
        //   9: ldc 32
        //   11: invokevirtual 36	android/os/Parcel:writeInterfaceToken	(Ljava/lang/String;)V
        //   14: aload_1
        //   15: ifnull +43 -> 58
        //   18: aload_1
        //   19: invokeinterface 122 1 0
        //   24: astore_1
        //   25: aload_2
        //   26: aload_1
        //   27: invokevirtual 90	android/os/Parcel:writeStrongBinder	(Landroid/os/IBinder;)V
        //   30: aload_0
        //   31: getfield 18	com/google/android/gms/internal/zzep$zza$zza:zzrp	Landroid/os/IBinder;
        //   34: bipush 24
        //   36: aload_2
        //   37: aload_3
        //   38: iconst_0
        //   39: invokeinterface 42 5 0
        //   44: pop
        //   45: aload_3
        //   46: invokevirtual 45	android/os/Parcel:readException	()V
        //   49: aload_3
        //   50: invokevirtual 48	android/os/Parcel:recycle	()V
        //   53: aload_2
        //   54: invokevirtual 48	android/os/Parcel:recycle	()V
        //   57: return
        //   58: aconst_null
        //   59: astore_1
        //   60: goto -35 -> 25
        //   63: astore_1
        //   64: aload_3
        //   65: invokevirtual 48	android/os/Parcel:recycle	()V
        //   68: aload_2
        //   69: invokevirtual 48	android/os/Parcel:recycle	()V
        //   72: aload_1
        //   73: athrow
        // Local variable table:
        //   start	length	slot	name	signature
        //   0	74	0	this	zza
        //   0	74	1	paramZznt	zznt
        //   3	66	2	localParcel1	Parcel
        //   7	58	3	localParcel2	Parcel
        // Exception table:
        //   from	to	target	type
        //   8	14	63	finally
        //   18	25	63	finally
        //   25	49	63	finally
      }
      
      public boolean zzb(zzdy paramZzdy)
        throws RemoteException
      {
        boolean bool = true;
        Parcel localParcel1 = Parcel.obtain();
        Parcel localParcel2 = Parcel.obtain();
        for (;;)
        {
          try
          {
            localParcel1.writeInterfaceToken("com.google.android.gms.ads.internal.client.IAdManager");
            if (paramZzdy != null)
            {
              localParcel1.writeInt(1);
              paramZzdy.writeToParcel(localParcel1, 0);
              zzrp.transact(4, localParcel1, localParcel2, 0);
              localParcel2.readException();
              int i = localParcel2.readInt();
              if (i != 0) {
                return bool;
              }
            }
            else
            {
              localParcel1.writeInt(0);
              continue;
            }
            bool = false;
          }
          finally
          {
            localParcel2.recycle();
            localParcel1.recycle();
          }
        }
      }
      
      public zzd zzbC()
        throws RemoteException
      {
        Parcel localParcel1 = Parcel.obtain();
        Parcel localParcel2 = Parcel.obtain();
        try
        {
          localParcel1.writeInterfaceToken("com.google.android.gms.ads.internal.client.IAdManager");
          zzrp.transact(1, localParcel1, localParcel2, 0);
          localParcel2.readException();
          zzd localZzd = zzd.zza.zzcd(localParcel2.readStrongBinder());
          return localZzd;
        }
        finally
        {
          localParcel2.recycle();
          localParcel1.recycle();
        }
      }
      
      /* Error */
      public zzec zzbD()
        throws RemoteException
      {
        // Byte code:
        //   0: invokestatic 30	android/os/Parcel:obtain	()Landroid/os/Parcel;
        //   3: astore_2
        //   4: invokestatic 30	android/os/Parcel:obtain	()Landroid/os/Parcel;
        //   7: astore_3
        //   8: aload_2
        //   9: ldc 32
        //   11: invokevirtual 36	android/os/Parcel:writeInterfaceToken	(Ljava/lang/String;)V
        //   14: aload_0
        //   15: getfield 18	com/google/android/gms/internal/zzep$zza$zza:zzrp	Landroid/os/IBinder;
        //   18: bipush 12
        //   20: aload_2
        //   21: aload_3
        //   22: iconst_0
        //   23: invokeinterface 42 5 0
        //   28: pop
        //   29: aload_3
        //   30: invokevirtual 45	android/os/Parcel:readException	()V
        //   33: aload_3
        //   34: invokevirtual 60	android/os/Parcel:readInt	()I
        //   37: ifeq +26 -> 63
        //   40: getstatic 144	com/google/android/gms/internal/zzec:CREATOR	Landroid/os/Parcelable$Creator;
        //   43: aload_3
        //   44: invokeinterface 150 2 0
        //   49: checkcast 78	com/google/android/gms/internal/zzec
        //   52: astore_1
        //   53: aload_3
        //   54: invokevirtual 48	android/os/Parcel:recycle	()V
        //   57: aload_2
        //   58: invokevirtual 48	android/os/Parcel:recycle	()V
        //   61: aload_1
        //   62: areturn
        //   63: aconst_null
        //   64: astore_1
        //   65: goto -12 -> 53
        //   68: astore_1
        //   69: aload_3
        //   70: invokevirtual 48	android/os/Parcel:recycle	()V
        //   73: aload_2
        //   74: invokevirtual 48	android/os/Parcel:recycle	()V
        //   77: aload_1
        //   78: athrow
        // Local variable table:
        //   start	length	slot	name	signature
        //   0	79	0	this	zza
        //   52	13	1	localZzec	zzec
        //   68	10	1	localObject	Object
        //   3	71	2	localParcel1	Parcel
        //   7	63	3	localParcel2	Parcel
        // Exception table:
        //   from	to	target	type
        //   8	53	68	finally
      }
      
      public void zzbF()
        throws RemoteException
      {
        Parcel localParcel1 = Parcel.obtain();
        Parcel localParcel2 = Parcel.obtain();
        try
        {
          localParcel1.writeInterfaceToken("com.google.android.gms.ads.internal.client.IAdManager");
          zzrp.transact(11, localParcel1, localParcel2, 0);
          localParcel2.readException();
          return;
        }
        finally
        {
          localParcel2.recycle();
          localParcel1.recycle();
        }
      }
      
      public zzew zzbG()
        throws RemoteException
      {
        Parcel localParcel1 = Parcel.obtain();
        Parcel localParcel2 = Parcel.obtain();
        try
        {
          localParcel1.writeInterfaceToken("com.google.android.gms.ads.internal.client.IAdManager");
          zzrp.transact(26, localParcel1, localParcel2, 0);
          localParcel2.readException();
          zzew localZzew = zzew.zza.zzw(localParcel2.readStrongBinder());
          return localZzew;
        }
        finally
        {
          localParcel2.recycle();
          localParcel1.recycle();
        }
      }
    }
  }
}
