package com.google.android.gms.internal;

import android.os.Binder;
import android.os.IBinder;
import android.os.IInterface;
import android.os.Parcel;
import android.os.RemoteException;

public abstract interface zzew
  extends IInterface
{
  public abstract float getAspectRatio()
    throws RemoteException;
  
  public abstract int getPlaybackState()
    throws RemoteException;
  
  public abstract boolean isMuted()
    throws RemoteException;
  
  public abstract void pause()
    throws RemoteException;
  
  public abstract void play()
    throws RemoteException;
  
  public abstract void zza(zzex paramZzex)
    throws RemoteException;
  
  public abstract float zzeR()
    throws RemoteException;
  
  public abstract float zzeS()
    throws RemoteException;
  
  public abstract void zzn(boolean paramBoolean)
    throws RemoteException;
  
  public static abstract class zza
    extends Binder
    implements zzew
  {
    public zza()
    {
      attachInterface(this, "com.google.android.gms.ads.internal.client.IVideoController");
    }
    
    public static zzew zzw(IBinder paramIBinder)
    {
      if (paramIBinder == null) {
        return null;
      }
      IInterface localIInterface = paramIBinder.queryLocalInterface("com.google.android.gms.ads.internal.client.IVideoController");
      if ((localIInterface != null) && ((localIInterface instanceof zzew))) {
        return (zzew)localIInterface;
      }
      return new zza(paramIBinder);
    }
    
    public IBinder asBinder()
    {
      return this;
    }
    
    public boolean onTransact(int paramInt1, Parcel paramParcel1, Parcel paramParcel2, int paramInt2)
      throws RemoteException
    {
      int i = 0;
      boolean bool = false;
      switch (paramInt1)
      {
      default: 
        return super.onTransact(paramInt1, paramParcel1, paramParcel2, paramInt2);
      case 1598968902: 
        paramParcel2.writeString("com.google.android.gms.ads.internal.client.IVideoController");
        return true;
      case 1: 
        paramParcel1.enforceInterface("com.google.android.gms.ads.internal.client.IVideoController");
        play();
        paramParcel2.writeNoException();
        return true;
      case 2: 
        paramParcel1.enforceInterface("com.google.android.gms.ads.internal.client.IVideoController");
        pause();
        paramParcel2.writeNoException();
        return true;
      case 3: 
        paramParcel1.enforceInterface("com.google.android.gms.ads.internal.client.IVideoController");
        if (paramParcel1.readInt() != 0) {
          bool = true;
        }
        zzn(bool);
        paramParcel2.writeNoException();
        return true;
      case 4: 
        paramParcel1.enforceInterface("com.google.android.gms.ads.internal.client.IVideoController");
        bool = isMuted();
        paramParcel2.writeNoException();
        paramInt1 = i;
        if (bool) {
          paramInt1 = 1;
        }
        paramParcel2.writeInt(paramInt1);
        return true;
      case 5: 
        paramParcel1.enforceInterface("com.google.android.gms.ads.internal.client.IVideoController");
        paramInt1 = getPlaybackState();
        paramParcel2.writeNoException();
        paramParcel2.writeInt(paramInt1);
        return true;
      case 6: 
        paramParcel1.enforceInterface("com.google.android.gms.ads.internal.client.IVideoController");
        f = zzeR();
        paramParcel2.writeNoException();
        paramParcel2.writeFloat(f);
        return true;
      case 7: 
        paramParcel1.enforceInterface("com.google.android.gms.ads.internal.client.IVideoController");
        f = zzeS();
        paramParcel2.writeNoException();
        paramParcel2.writeFloat(f);
        return true;
      case 8: 
        paramParcel1.enforceInterface("com.google.android.gms.ads.internal.client.IVideoController");
        zza(zzex.zza.zzx(paramParcel1.readStrongBinder()));
        paramParcel2.writeNoException();
        return true;
      }
      paramParcel1.enforceInterface("com.google.android.gms.ads.internal.client.IVideoController");
      float f = getAspectRatio();
      paramParcel2.writeNoException();
      paramParcel2.writeFloat(f);
      return true;
    }
    
    private static class zza
      implements zzew
    {
      private IBinder zzrp;
      
      zza(IBinder paramIBinder)
      {
        zzrp = paramIBinder;
      }
      
      public IBinder asBinder()
      {
        return zzrp;
      }
      
      public float getAspectRatio()
        throws RemoteException
      {
        Parcel localParcel1 = Parcel.obtain();
        Parcel localParcel2 = Parcel.obtain();
        try
        {
          localParcel1.writeInterfaceToken("com.google.android.gms.ads.internal.client.IVideoController");
          zzrp.transact(9, localParcel1, localParcel2, 0);
          localParcel2.readException();
          float f = localParcel2.readFloat();
          return f;
        }
        finally
        {
          localParcel2.recycle();
          localParcel1.recycle();
        }
      }
      
      public int getPlaybackState()
        throws RemoteException
      {
        Parcel localParcel1 = Parcel.obtain();
        Parcel localParcel2 = Parcel.obtain();
        try
        {
          localParcel1.writeInterfaceToken("com.google.android.gms.ads.internal.client.IVideoController");
          zzrp.transact(5, localParcel1, localParcel2, 0);
          localParcel2.readException();
          int i = localParcel2.readInt();
          return i;
        }
        finally
        {
          localParcel2.recycle();
          localParcel1.recycle();
        }
      }
      
      public boolean isMuted()
        throws RemoteException
      {
        boolean bool = false;
        Parcel localParcel1 = Parcel.obtain();
        Parcel localParcel2 = Parcel.obtain();
        try
        {
          localParcel1.writeInterfaceToken("com.google.android.gms.ads.internal.client.IVideoController");
          zzrp.transact(4, localParcel1, localParcel2, 0);
          localParcel2.readException();
          int i = localParcel2.readInt();
          if (i != 0) {
            bool = true;
          }
          return bool;
        }
        finally
        {
          localParcel2.recycle();
          localParcel1.recycle();
        }
      }
      
      public void pause()
        throws RemoteException
      {
        Parcel localParcel1 = Parcel.obtain();
        Parcel localParcel2 = Parcel.obtain();
        try
        {
          localParcel1.writeInterfaceToken("com.google.android.gms.ads.internal.client.IVideoController");
          zzrp.transact(2, localParcel1, localParcel2, 0);
          localParcel2.readException();
          return;
        }
        finally
        {
          localParcel2.recycle();
          localParcel1.recycle();
        }
      }
      
      public void play()
        throws RemoteException
      {
        Parcel localParcel1 = Parcel.obtain();
        Parcel localParcel2 = Parcel.obtain();
        try
        {
          localParcel1.writeInterfaceToken("com.google.android.gms.ads.internal.client.IVideoController");
          zzrp.transact(1, localParcel1, localParcel2, 0);
          localParcel2.readException();
          return;
        }
        finally
        {
          localParcel2.recycle();
          localParcel1.recycle();
        }
      }
      
      /* Error */
      public void zza(zzex paramZzex)
        throws RemoteException
      {
        // Byte code:
        //   0: invokestatic 31	android/os/Parcel:obtain	()Landroid/os/Parcel;
        //   3: astore_2
        //   4: invokestatic 31	android/os/Parcel:obtain	()Landroid/os/Parcel;
        //   7: astore_3
        //   8: aload_2
        //   9: ldc 33
        //   11: invokevirtual 37	android/os/Parcel:writeInterfaceToken	(Ljava/lang/String;)V
        //   14: aload_1
        //   15: ifnull +43 -> 58
        //   18: aload_1
        //   19: invokeinterface 67 1 0
        //   24: astore_1
        //   25: aload_2
        //   26: aload_1
        //   27: invokevirtual 70	android/os/Parcel:writeStrongBinder	(Landroid/os/IBinder;)V
        //   30: aload_0
        //   31: getfield 18	com/google/android/gms/internal/zzew$zza$zza:zzrp	Landroid/os/IBinder;
        //   34: bipush 8
        //   36: aload_2
        //   37: aload_3
        //   38: iconst_0
        //   39: invokeinterface 43 5 0
        //   44: pop
        //   45: aload_3
        //   46: invokevirtual 46	android/os/Parcel:readException	()V
        //   49: aload_3
        //   50: invokevirtual 52	android/os/Parcel:recycle	()V
        //   53: aload_2
        //   54: invokevirtual 52	android/os/Parcel:recycle	()V
        //   57: return
        //   58: aconst_null
        //   59: astore_1
        //   60: goto -35 -> 25
        //   63: astore_1
        //   64: aload_3
        //   65: invokevirtual 52	android/os/Parcel:recycle	()V
        //   68: aload_2
        //   69: invokevirtual 52	android/os/Parcel:recycle	()V
        //   72: aload_1
        //   73: athrow
        // Local variable table:
        //   start	length	slot	name	signature
        //   0	74	0	this	zza
        //   0	74	1	paramZzex	zzex
        //   3	66	2	localParcel1	Parcel
        //   7	58	3	localParcel2	Parcel
        // Exception table:
        //   from	to	target	type
        //   8	14	63	finally
        //   18	25	63	finally
        //   25	49	63	finally
      }
      
      public float zzeR()
        throws RemoteException
      {
        Parcel localParcel1 = Parcel.obtain();
        Parcel localParcel2 = Parcel.obtain();
        try
        {
          localParcel1.writeInterfaceToken("com.google.android.gms.ads.internal.client.IVideoController");
          zzrp.transact(6, localParcel1, localParcel2, 0);
          localParcel2.readException();
          float f = localParcel2.readFloat();
          return f;
        }
        finally
        {
          localParcel2.recycle();
          localParcel1.recycle();
        }
      }
      
      public float zzeS()
        throws RemoteException
      {
        Parcel localParcel1 = Parcel.obtain();
        Parcel localParcel2 = Parcel.obtain();
        try
        {
          localParcel1.writeInterfaceToken("com.google.android.gms.ads.internal.client.IVideoController");
          zzrp.transact(7, localParcel1, localParcel2, 0);
          localParcel2.readException();
          float f = localParcel2.readFloat();
          return f;
        }
        finally
        {
          localParcel2.recycle();
          localParcel1.recycle();
        }
      }
      
      public void zzn(boolean paramBoolean)
        throws RemoteException
      {
        int i = 0;
        Parcel localParcel1 = Parcel.obtain();
        Parcel localParcel2 = Parcel.obtain();
        try
        {
          localParcel1.writeInterfaceToken("com.google.android.gms.ads.internal.client.IVideoController");
          if (paramBoolean) {
            i = 1;
          }
          localParcel1.writeInt(i);
          zzrp.transact(3, localParcel1, localParcel2, 0);
          localParcel2.readException();
          return;
        }
        finally
        {
          localParcel2.recycle();
          localParcel1.recycle();
        }
      }
    }
  }
}
